tysig/__init__.py
tysig/tyerrors.py
tysig/tysig.py
ty_sig-0.1.5.dist-info/LICENSE
ty_sig-0.1.5.dist-info/METADATA
ty_sig-0.1.5.dist-info/WHEEL
ty_sig-0.1.5.dist-info/top_level.txt
ty_sig-0.1.5.dist-info/RECORD
